{
  "Items": [
    {
      
      "description": "Joseph Ducreax Memes", 
      "essay": null, 
      "id": 1600, 
      "lists_id": 1, 
      "name": "Kinsperson", 
      "pic_ url": null, 
      "published": null, 
      "rank": 5, 
      "updated": null, 
      "url": "https://jukebox9.files.wordpress.com/2015/08/21.jpg"
    }, 
    {
      "description": "Joseph Ducreax Memes", 
      "essay": null, 
      "id": 1601, 
      "lists_id": 1, 
      "name": "They Observe Me Voyaging", 
      "pic_ url": null, 
      "published": null, 
      "rank": 2, 
      "updated": null, 
      "url": "https://s-media-cache-ak0.pinimg.com/236x/50/5d/0e/505d0e7897b1bd94e26b85eb028c58e2.jpg"
    }, 
    {
      "description": "Joseph Ducreax Memes", 
      "essay": null, 
      "id": 1602, 
      "lists_id": 1, 
      "name": "You Doth Aspire", 
      "pic_ url": null, 
      "published": null, 
      "rank": 1, 
      "updated": null, 
      "url": "https://jukebox9.files.wordpress.com/2015/08/31.jpg"
    }, 
    {
      "description": "Joseph Ducreax Memes", 
      "essay": null, 
      "id": 1603, 
      "lists_id": 1, 
      "name": "Quiet Down", 
      "pic_ url": null, 
      "published": null, 
      "rank": 4, 
      "updated": null, 
      "url": "http://i2.kym-cdn.com/photos/images/original/000/464/285/17b.png"
    }, 
    {
      "description": "Sooooo Cute", 
      "essay": null, 
      "id": 1604, 
      "lists_id": 3, 
      "name": "BubbleGoth", 
      "pic_ url": null, 
      "published": null, 
      "rank": 5, 
      "updated": null, 
      "url": "http://cdn.buzznet.com/assets/users16/kerli/default/cutest-cats--large-msg-134704087653.jpg"
    }, 
    {
      "description": "The eyes!! omg!", 
      "essay": null, 
      "id": 1605, 
      "lists_id": 3, 
      "name": "Pinterest", 
      "pic_ url": "Nonewewewe", 
      "published": null, 
      "rank": 2, 
      "updated": null, 
      "url": "https://s-media-cache-ak0.pinimg.com/736x/8c/99/e3/8c99e3483387df6395da674a6b5dee4c.jpg"
    }, 
    {
      "description": "Sooooo Cute", 
      "essay": null, 
      "id": 1606, 
      "lists_id": 3, 
      "name": "Adorable", 
      "pic_ url": null, 
      "published": null, 
      "rank": 6, 
      "updated": null, 
      "url": "http://amazinganimalphotos.com/wp-content/uploads/2013/04/cutest-cat-picture-ever.jpg"
    }, 
    {
      "description": "Sooooo Cute", 
      "essay": null, 
      "id": 1607, 
      "lists_id": 3, 
      "name": "Kerli", 
      "pic_ url": null, 
      "published": null, 
      "rank": 9, 
      "updated": null, 
      "url": "http://cdn.buzznet.com/assets/users16/kerli/default/cutest-cats--large-msg-134704089222.jpg"
    }, 
    {
      "description": "Dreamy", 
      "essay": null, 
      "id": 1608, 
      "lists_id": 3, 
      "name": "Cute", 
      "pic_ url": null, 
      "published": null, 
      "rank": 4, 
      "updated": null, 
      "url": "http://cdn.buzznet.com/assets/users16/kerli/default/cutest-cats--large-msg-134704090282.jpg"
    }, 
    {
      "description": "We've had enough coffee!!", 
      "essay": null, 
      "id": 1609, 
      "lists_id": 3, 
      "name": "Cups", 
      "pic_ url": null, 
      "published": null, 
      "rank": 3, 
      "updated": null, 
      "url": "http://joyofsix.typepad.com/joyofsix/images/44334153_3e9114058d.jpg"
    }, 
    {
      "description": "He thinks he's people!", 
      "essay": null, 
      "id": 1610, 
      "lists_id": 3, 
      "name": "Sleeping", 
      "pic_ url": null, 
      "published": null, 
      "rank": 1, 
      "updated": null, 
      "url": "http://cdn-1.innocentenglish.com/cute-animals/cute-kitten-3.jpg"
    }, 
    {
      "description": "All you need to know about any language FAST!", 
      "essay": null, 
      "id": 1611, 
      "lists_id": 2, 
      "name": "Derek Banas", 
      "pic_ url": null, 
      "published": null, 
      "rank": 1, 
      "updated": null, 
      "url": "https://yt3.ggpht.com/-SN1RQ4kN5bM/AAAAAAAAAAI/AAAAAAAAAAA/T39gSKk4e2g/s176-c-k-no/photo.jpg"
    }, 
    {
      "description": "This guy has videos on machine learnin", 
      "essay": null, 
      "id": 1612, 
      "lists_id": 2, 
      "name": "Sentdex", 
      "pic_ url": null, 
      "published": null, 
      "rank": 2, 
      "updated": null, 
      "url": "https://yt3.ggpht.com/-kHTbb6oDqmY/AAAAAAAAAAI/AAAAAAAAAAA/BHWd_jlJmJU/s176-c-k-no/photo.jpg"
    }, 
    {
      "description": "Best Video with a chart showing how all the technologies of Web Development fit together. ", 
      "essay": null, 
      "id": 1613, 
      "lists_id": 2, 
      "name": "Learn Code Academy", 
      "pic_ url": null, 
      "published": null, 
      "rank": 3, 
      "updated": null, 
      "url": "https://yt3.ggpht.com/-mW8hwFBRUNs/AAAAAAAAAAI/AAAAAAAAAAA/jVL9TZ64o7A/s88-c-k-no/photo.jpg"
    }, 
    {
      "description": "Hannah Davis", 
      "essay": null, 
      "id": 1700, 
      "lists_id": 4, 
      "name": "2015", 
      "pic_ url": null, 
      "published": null, 
      "rank": 1, 
      "updated": null, 
      "url": "http://img2-2.timeinc.net/people/i/2015/news/150223/sports-illustrated-cover-435.jpg"
    }, 
    {
      "description": "Hot", 
      "essay": null, 
      "id": 1701, 
      "lists_id": 4, 
      "name": "2010", 
      "pic_ url": null, 
      "published": null, 
      "rank": 2, 
      "updated": null, 
      "url": "http://media.nj.com/star-ledger/photo/2014/02/2010-si-coverjpg-4233bc57ddd6ecd3.jpg"
    }, 
    {
      "description": "Kate Upton", 
      "essay": null, 
      "id": 1702, 
      "lists_id": 4, 
      "name": "2012", 
      "pic_ url": null, 
      "published": null, 
      "rank": 3, 
      "updated": null, 
      "url": "http://amfblog.s3.amazonaws.com/wp-content/uploads/2015/02/Kate-Upton.jpg"
    }, 
    {
      "description": "Kate Upton", 
      "essay": null, 
      "id": 1703, 
      "lists_id": 4, 
      "name": "2013", 
      "pic_ url": null, 
      "published": null, 
      "rank": 4, 
      "updated": null, 
      "url": "http://www.boston.com/ae/celebrity/blog/popradar/Kate-Cover.jpg"
    }, 
    {
      "description": "Bar Rafaeli", 
      "essay": null, 
      "id": 1704, 
      "lists_id": 4, 
      "name": "2009", 
      "pic_ url": null, 
      "published": null, 
      "rank": 5, 
      "updated": null, 
      "url": "http://img2.timeinc.net/people/i/2014/sandbox/news/140203/si-covers/si-09-435.jpg"
    }, 
    {
      "description": "Marisa Miller", 
      "essay": null, 
      "id": 1705, 
      "lists_id": 4, 
      "name": "2008", 
      "pic_ url": null, 
      "published": null, 
      "rank": 6, 
      "updated": null, 
      "url": "http://img2.timeinc.net/people/i/2014/sandbox/news/140203/si-covers/si-08-435.jpg"
    }, 
    {
      "description": "Beach Party", 
      "essay": null, 
      "id": 1706, 
      "lists_id": 4, 
      "name": "2006", 
      "pic_ url": null, 
      "published": null, 
      "rank": 7, 
      "updated": null, 
      "url": "http://img2-2.timeinc.net/people/i/2014/sandbox/news/140203/si-covers/si-06-435.jpg"
    }    
  ]
}